{
    "osteosarcoma_9": "viz?labeling=\\#0",
    "ovarian_7_ROv": "viz?labeling=\\#0",
    "ovarian_1_LOv": "viz?labeling=\\#0",
    "prostate_34": "viz?labeling=\\#0",
    "prostate_22": "viz?labeling=\\#0",
    "prostate_29": "viz?labeling=\\#0",
    "osteosarcoma_3": "viz?labeling=\\#0",
    "ovarian_7_LOv": "viz?labeling=\\#0",
    "ovarian_1_ROv": "viz?labeling=\\#0",
    "prostate_32": "viz?labeling=\\#0",
    "lung_CRUK0063": "viz?labeling=\\#0",
    "prostate_24": "viz?labeling=\\#0",
    "prostate_12": "viz?labeling=\\#0",
    "osteosarcoma_2": "viz?labeling=\\#0",
    "ovarian_3_LOv": "viz?labeling=\\#0",
    "ovarian_9_LOv": "viz?labeling=\\#0",
    "prostate_31": "viz?labeling=\\#0",
    "ovarian_10_ROv": "viz?labeling=\\#0",
    "ovarian_4_ROv": "viz?labeling=\\#0",
    "prostate_10": "viz?labeling=\\#0",
    "ovarian_9_ROv": "viz?labeling=\\#0",
    "prostate_21": "viz?labeling=\\#0",
    "ovarian_2_ROv": "viz?labeling=\\#0",
    "ovarian_3_ROv": "viz?labeling=\\#0",
    "prostate_17": "viz?labeling=\\#0",
    "ovarian_4_LOv": "viz?labeling=\\#0"
}